pulumi_azuread/__init__.py
pulumi_azuread/_inputs.py
pulumi_azuread/_utilities.py
pulumi_azuread/access_package.py
pulumi_azuread/access_package_assignment_policy.py
pulumi_azuread/access_package_catalog.py
pulumi_azuread/access_package_catalog_role_assignment.py
pulumi_azuread/access_package_resource_catalog_association.py
pulumi_azuread/access_package_resource_package_association.py
pulumi_azuread/administrative_unit.py
pulumi_azuread/administrative_unit_member.py
pulumi_azuread/administrative_unit_role_member.py
pulumi_azuread/app_role_assignment.py
pulumi_azuread/application.py
pulumi_azuread/application_api_access.py
pulumi_azuread/application_app_role.py
pulumi_azuread/application_certificate.py
pulumi_azuread/application_fallback_public_client.py
pulumi_azuread/application_federated_identity_credential.py
pulumi_azuread/application_flexible_federated_identity_credential.py
pulumi_azuread/application_from_template.py
pulumi_azuread/application_identifier_uri.py
pulumi_azuread/application_known_clients.py
pulumi_azuread/application_optional_claims.py
pulumi_azuread/application_owner.py
pulumi_azuread/application_password.py
pulumi_azuread/application_permission_scope.py
pulumi_azuread/application_pre_authorized.py
pulumi_azuread/application_redirect_uris.py
pulumi_azuread/application_registration.py
pulumi_azuread/authentication_strength_policy.py
pulumi_azuread/claims_mapping_policy.py
pulumi_azuread/conditional_access_policy.py
pulumi_azuread/custom_directory_role.py
pulumi_azuread/directory_role.py
pulumi_azuread/directory_role_assignment.py
pulumi_azuread/directory_role_eligibility_schedule_request.py
pulumi_azuread/directory_role_member.py
pulumi_azuread/get_access_package.py
pulumi_azuread/get_access_package_catalog.py
pulumi_azuread/get_access_package_catalog_role.py
pulumi_azuread/get_administrative_unit.py
pulumi_azuread/get_application.py
pulumi_azuread/get_application_published_app_ids.py
pulumi_azuread/get_application_template.py
pulumi_azuread-6.8.0.dist-info/METADATA
pulumi_azuread-6.8.0.dist-info/WHEEL
pulumi_azuread-6.8.0.dist-info/top_level.txt
pulumi_azuread-6.8.0.dist-info/RECORD
